sfb/__init__.py
sfb/config.py
sfb/configure.py
sfb/entrypoint.py
sfb/estimator.py
sfb/cli/__init__.py
sfb/cli/main.py
tests/__init__.py
tests/conftest.py
tests/test_bq.py
tests/test_estimator.py
sfb-0.1.4.dist-info/LICENSE
sfb-0.1.4.dist-info/METADATA
sfb-0.1.4.dist-info/WHEEL
sfb-0.1.4.dist-info/entry_points.txt
sfb-0.1.4.dist-info/top_level.txt
sfb-0.1.4.dist-info/RECORD
