Metadata-Version: 2.1
Name: sfb
Version: 0.1.4
Summary: SQL tester and cost estimator for Google BigQuery
Home-page: https://github.com/tosh223/sfb
Author: Toshifumi Tsutsumi
License: UNKNOWN
Keywords: bigquery,sql,testing,development
Platform: UNKNOWN
Classifier: Development Status :: 4 - Beta
Classifier: Intended Audience :: Developers
Classifier: Topic :: Software Development :: Testing
Classifier: License :: OSI Approved :: MIT License
Classifier: Programming Language :: Python :: 3 :: Only
Requires-Python: >=3.6, <4
Requires-Dist: google-cloud-bigquery
Requires-Dist: pyyaml
